src/__init__.py
src/common/Common.py
src/common/Exceptions.py
src/common/__init__.py
src/models/Attendee.py
src/models/Entrant.py
src/models/Event.py
src/models/GGSet.py
src/models/Organizer.py
src/models/Phase.py
src/models/PhaseGroup.py
src/models/Player.py
src/models/Stream.py
src/models/StreamQueue.py
src/models/Tournament.py
src/models/User.py
src/models/Venue.py
src/models/__init__.py
src/queries/Event_Queries.py
src/queries/Phase_Group_Queries.py
src/queries/Phase_Queries.py
src/queries/Schema.py
src/queries/Tournament_Queries.py
src/queries/__init__.py
src/util/Initializer.py
src/util/Logger.py
src/util/NetworkInterface.py
src/util/Query.py
src/util/QueryFactory.py
src/util/QueryQueue.py
src/util/QueryQueueDaemon.py
src/util/QueryQueueElement.py
src/util/ThreadFactory.py
src/util/TokenHandler.py
src/util/__init__.py
smashggpy-0.0.9.dist-info/LICENSE
smashggpy-0.0.9.dist-info/METADATA
smashggpy-0.0.9.dist-info/WHEEL
smashggpy-0.0.9.dist-info/top_level.txt
smashggpy-0.0.9.dist-info/RECORD
