Metadata-Version: 2.1
Name: smashggpy
Version: 0.0.9
Summary: Python SDK for smash.gg's public api
Home-page: https://github.com/BrandonCookeDev/smashgg.py
Author: Brandon Cooke
Author-email: brandoncookedev@gmail.com
License: UNKNOWN
Platform: UNKNOWN
Classifier: Programming Language :: Python :: 3
Classifier: License :: OSI Approved :: MIT License
Classifier: Operating System :: OS Independent
